{
  "title": ".filtered-FE5A421F-96C6-4567-98CF-15444DC97FEB.mp4",
  "description": "",
  "imageViews": "94",
  "creationTime": {
    "timestamp": "1527997877",
    "formatted": "Jun 3, 2018, 3:51:17 AM UTC"
  },
  "photoTakenTime": {
    "timestamp": "1527642501",
    "formatted": "May 30, 2018, 1:08:21 AM UTC"
  },
  "geoData": {
    "latitude": 0.0,
    "longitude": 0.0,
    "altitude": 0.0,
    "latitudeSpan": 0.0,
    "longitudeSpan": 0.0
  },
  "url": "https://photos.google.com/photo/AF1QipMyce_rV_777U3g7Mf4oQV7ZACK3uEULSZEhQWN",
  "googlePhotosOrigin": {
    "mobileUpload": {
      "deviceType": "IOS_PHONE"
    }
  }
}