{
  "title": ".filtered-878F0EDA-9EA4-4BB5-B22A-8BF2ABEF5A31.mp4",
  "description": "",
  "imageViews": "78",
  "creationTime": {
    "timestamp": "1524478139",
    "formatted": "Apr 23, 2018, 10:08:59 AM UTC"
  },
  "photoTakenTime": {
    "timestamp": "1523977067",
    "formatted": "Apr 17, 2018, 2:57:47 PM UTC"
  },
  "geoData": {
    "latitude": 0.0,
    "longitude": 0.0,
    "altitude": 0.0,
    "latitudeSpan": 0.0,
    "longitudeSpan": 0.0
  },
  "url": "https://photos.google.com/photo/AF1QipPp5YTTtEuyNSvJJ7tuQjVEYtvbqXajvdpfSvBh",
  "googlePhotosOrigin": {
    "mobileUpload": {
      "deviceType": "IOS_PHONE"
    }
  }
}