{
  "title": "IMG_0362.HEIC",
  "description": "",
  "imageViews": "55",
  "creationTime": {
    "timestamp": "1541530815",
    "formatted": "Nov 6, 2018, 7:00:15 PM UTC"
  },
  "photoTakenTime": {
    "timestamp": "1541280201",
    "formatted": "Nov 3, 2018, 9:23:21 PM UTC"
  },
  "geoData": {
    "latitude": 42.2662556,
    "longitude": -83.74984719999999,
    "altitude": 270.2331969608416,
    "latitudeSpan": 0.0,
    "longitudeSpan": 0.0
  },
  "geoDataExif": {
    "latitude": 42.2662556,
    "longitude": -83.74984719999999,
    "altitude": 270.2331969608416,
    "latitudeSpan": 0.0,
    "longitudeSpan": 0.0
  },
  "url": "https://photos.google.com/photo/AF1QipP1nte8Uc52kCUdMWRTN3S5js0Inb_q-vXm6IeK",
  "googlePhotosOrigin": {
    "mobileUpload": {
      "deviceType": "IOS_PHONE"
    }
  }
}